README
setup.py
src/pngdefry/__init__.py
src/pngdefry/miniz.c
src/pngdefry/miniz.h
src/pngdefry/pngdefry.c
src/pngdefry.egg-info/PKG-INFO
src/pngdefry.egg-info/SOURCES.txt
src/pngdefry.egg-info/dependency_links.txt
src/pngdefry.egg-info/entry_points.txt
src/pngdefry.egg-info/not-zip-safe
src/pngdefry.egg-info/top_level.txt