Metadata-Version: 1.0
Name: pngdefry
Version: 0.4
Summary: Remove iPhone specific optimizations from PNG files
Home-page: https://github.com/ApplauseAQI/pngdefry
Author: Piotr Duda Applause
Author-email: pduda@applause.com
License: MIT
Platform: UNKNOWN
